MANIFEST.in
README.rst
requirements.txt
setup.py
bullock/__init__.py
bullock.egg-info/PKG-INFO
bullock.egg-info/SOURCES.txt
bullock.egg-info/dependency_links.txt
bullock.egg-info/requires.txt
bullock.egg-info/top_level.txt