Metadata-Version: 1.0
Name: bullock
Version: 0.0.3
Summary: Distributed lock using Redis
Home-page: UNKNOWN
Author: Juarez Bochi
Author-email: UNKNOWN
License: UNKNOWN
Platform: UNKNOWN
